setup.py
bart_api/__init__.py
bart_api.egg-info/PKG-INFO
bart_api.egg-info/SOURCES.txt
bart_api.egg-info/dependency_links.txt
bart_api.egg-info/top_level.txt
bart_api/test/__init__.py
bart_api/test/test_bart_api.py