Metadata-Version: 1.0
Name: bart-api
Version: 0.1
Summary: a python client that interacts with the bay area rapid transit api
Home-page: http://github.com/projectdelphai/bart_api
Author: Reuben Castelino
Author-email: projetdelphai@gmail.com
License: MIT
Platform: UNKNOWN
